Metadata-Version: 2.1
Name: openapi-client
Version: 1.0.0
Summary: server
Home-page: UNKNOWN
Author: OpenAPI Generator community
Author-email: team@openapitools.org
License: UNKNOWN
Keywords: OpenAPI,OpenAPI-Generator,server
Platform: UNKNOWN
Requires-Python: >=3.6
Requires-Dist: urllib3 (>=1.25.3)
Requires-Dist: python-dateutil
